app_config/__init__.py
app_config/asgi.py
app_config/settings.py
app_config/urls.py
app_config/wsgi.py
rest_core/__init__.py
rest_core/apps.py
rest_core/build_absolute_uri/__init__.py
rest_core/build_absolute_uri/build_absolute_uri.py
rest_core/cache/__init__.py
rest_core/cache/mixins/__init__.py
rest_core/cache/mixins/cache_mixin.py
rest_core/django/__init__.py
rest_core/django/views.py
rest_core/email_service/__init__.py
rest_core/email_service/email_service.py
rest_core/email_service/exceptions.py
rest_core/email_service/models.py
rest_core/email_service/types.py
rest_core/email_service/validators.py
rest_core/exceptions/__init__.py
rest_core/exceptions/exceptions.py
rest_core/management/__init__.py
rest_core/management/commands/__init__.py
rest_core/management/commands/mock_records.py
rest_core/middlewares/__init__.py
rest_core/middlewares/middlewares.py
rest_core/migrations/__init__.py
rest_core/pagination/__init__.py
rest_core/pagination/page_number_pagination.py
rest_core/pagination/paginate_and_serialize_data.py
rest_core/renderers/__init__.py
rest_core/renderers/structured_json_renderer.py
rest_core/response/__init__.py
rest_core/response/response.py
rest_core/response/types.py
rest_core/serializers/__init__.py
rest_core/serializers/mixins/__init__.py
rest_core/serializers/mixins/file_field_url_mixin.py
rest_core/serializers/mixins/records_creation_mixin.py
rest_core/throttle_inspector/__init__.py
rest_core/throttle_inspector/throttle_inspector.py
rest_core/views/__init__.py
rest_core/views/model_choice_field_api_view.py
rest_core/views/mixins/__init__.py
rest_core/views/mixins/model_choice_field_mixin.py
rest_core/views/mixins/model_object_mixin.py
rest_core/viewsets/__init__.py
rest_core/viewsets/mixins/__init__.py
rest_core/viewsets/mixins/action_message_mixin.py
rest_core/viewsets/mixins/model_choice_field_action_mixin.py
rest_core-0.1.51.dist-info/licenses/LICENSE
todo_app/__init__.py
todo_app/admin.py
todo_app/apps.py
todo_app/tests.py
todo_app/urls.py
todo_app/migrations/0001_initial.py
rest_core-0.1.51.dist-info/METADATA
rest_core-0.1.51.dist-info/WHEEL
rest_core-0.1.51.dist-info/top_level.txt
rest_core-0.1.51.dist-info/RECORD
