Metadata-Version: 2.4
Name: rest-core
Version: 0.1.51
Summary: A lightweight Django package to enhance your Django REST Framework (DRF)
Author-email: shailesh pandit <shaileshpandit141@gmail.com>
License: MIT License
Project-URL: Homepage, https://github.com/shaileshpandit141/rest-core
Project-URL: Repository, https://github.com/shaileshpandit141/rest-core
Classifier: Development Status :: 5 - Production/Stable
Classifier: Intended Audience :: Developers
Classifier: Topic :: Software Development :: Libraries
Classifier: License :: OSI Approved :: MIT License
Classifier: Programming Language :: Python
Classifier: Programming Language :: Python :: 3
Classifier: Programming Language :: Python :: 3.10
Classifier: Programming Language :: Python :: 3.11
Classifier: Framework :: Django
Classifier: Framework :: Django :: 3.2
Classifier: Framework :: Django :: 4.0
Classifier: Framework :: Django :: 4.1
Classifier: Framework :: Django :: 4.2
Classifier: Framework :: Django :: 5.0
Classifier: Operating System :: OS Independent
Requires-Python: >=3.10
License-File: LICENSE
Requires-Dist: django>=5.2
Requires-Dist: djangorestframework>=3.16.0
Requires-Dist: pydantic>=2.11.3
Requires-Dist: pytz>=2025.2
Dynamic: license-file
